repeatable/__init__.py
repeatable/repeatable.py
repeatable/reitertools/__init__.py
repeatable/reitertools/combinations.py
repeatable/reitertools/combinations_with_replacement.py
repeatable/reitertools/cycle.py
repeatable/reitertools/permutations.py
repeatable/reitertools/product.py
repeatable-0.0.1.dist-info/licenses/LICENSE
repeatable-0.0.1.dist-info/METADATA
repeatable-0.0.1.dist-info/WHEEL
repeatable-0.0.1.dist-info/top_level.txt
repeatable-0.0.1.dist-info/RECORD
